mighty_sdk_core/auth/oauth.py
mighty_sdk_core/auth/secret.py
mighty_sdk_core/auth/types.py
mighty_sdk_core/crypto/aad_meta.py
mighty_sdk_core/crypto/asymmetric_encryption.py
mighty_sdk_core/crypto/json_datagram.py
mighty_sdk_core/crypto/symmetric_encryption.py
mighty_sdk_core/crypto/tagged_secret_box.py
mighty_sdk_core/crypto/utils.py
mighty_sdk_core/data/decrypt.py
mighty_sdk_core/data/types.py
mighty_sdk_core/mighty/README.md
mighty_sdk_core/mighty/application_client.py
mighty_sdk_core/mighty/client.py
mighty_sdk_core/mighty/types.py
mighty_sdk_core/mighty/user_data_client.py
mighty_sdk_core-0.1.10.dist-info/METADATA
mighty_sdk_core-0.1.10.dist-info/WHEEL
mighty_sdk_core-0.1.10.dist-info/RECORD
